x21_sdk/__init__.py
x21_sdk/auth/__init__.py
x21_sdk/client/__init__.py
x21_sdk/client/api/__init__.py
x21_sdk/client/api/order/__init__.py
x21_sdk/client/api/order/create_primary_market_order.py
x21_sdk/client/api/order/get_wallet_orders.py
x21_sdk/client/api/public_market_data/__init__.py
x21_sdk/client/api/public_market_data/get_financial_instrument.py
x21_sdk/client/api/public_market_data/get_financial_instruments.py
x21_sdk/client/api/public_market_data/get_order_book_price_levels.py
x21_sdk/client/api/public_market_data/get_order_book_top_orders.py
x21_sdk/client/api/public_market_data/get_post_trade_transparency.py
x21_sdk/client/api/public_market_data/get_price_history_ohlc.py
x21_sdk/client/api/public_market_data/get_trade_info.py
x21_sdk/client/api/public_market_data/get_trading_pair.py
x21_sdk/client/api/public_market_data/get_trading_pairs.py
x21_sdk/client/api/trade/__init__.py
x21_sdk/client/api/trade/get_wallet_trades.py
x21_sdk/client/api/wallet/__init__.py
x21_sdk/client/api/wallet/get_wallet_by_address.py
x21_sdk/client/client.py
x21_sdk/client/errors.py
x21_sdk/client/models/__init__.py
x21_sdk/client/models/address_data.py
x21_sdk/client/models/app_error.py
x21_sdk/client/models/asset_class_of_underlying_enum.py
x21_sdk/client/models/block_chain_enum.py
x21_sdk/client/models/commodity_derivative_final_price_type_enum.py
x21_sdk/client/models/commodity_derivative_size_specification_enum.py
x21_sdk/client/models/commodity_derivative_transaction_type_enum.py
x21_sdk/client/models/commodity_derivatives_further_sub_product_enum.py
x21_sdk/client/models/commodity_derivatives_product_enum.py
x21_sdk/client/models/commodity_derivatives_sub_product_enum.py
x21_sdk/client/models/contracts_for_difference_underlying_type_enum.py
x21_sdk/client/models/emission_allowance_sub_type_enum.py
x21_sdk/client/models/equity_derivative_parameter_type_enum.py
x21_sdk/client/models/equity_derivative_underlying_type_enum.py
x21_sdk/client/models/finality_status_enum.py
21x_sdk-1.0.1.dist-info/LICENSE
21x_sdk-1.0.1.dist-info/METADATA
21x_sdk-1.0.1.dist-info/WHEEL
21x_sdk-1.0.1.dist-info/RECORD
