Metadata-Version: 2.3
Name: 21x-sdk
Version: 1.0.1
Summary: Library to interact with 21X platform.
License: Apache-2.0
Requires-Python: >=3.9,<4
Classifier: License :: OSI Approved :: Apache Software License
Classifier: Programming Language :: Python :: 3
Classifier: Programming Language :: Python :: 3.9
Classifier: Programming Language :: Python :: 3.10
Classifier: Programming Language :: Python :: 3.11
Classifier: Programming Language :: Python :: 3.12
Classifier: Programming Language :: Python :: 3.13
Requires-Dist: attrs (>=25.1.0,<26.0.0)
Requires-Dist: authlib (>=1.5.2,<2.0.0)
Requires-Dist: httpx (>=0.28.1,<0.29.0)
Requires-Dist: python-dateutil (>=2.8.0,<3.0.0)
Requires-Dist: web3 (==7.6.0)
